rcghci/__init__.py
rcghci/__main__.py
rcghci/rcghci.py
rcghci/rcghci_nvim.py
rcrepl/__init__.py
rcrepl/__main__.py
rcrepl/rcelm.py
rcrepl/rcghci.py
rcrepl/rcrepl.py
rcrepl/rcrepl_nvim.py
rcrepl/rcrepl_vim.py
rcrepl-2.1.6.dist-info/DESCRIPTION.rst
rcrepl-2.1.6.dist-info/METADATA
rcrepl-2.1.6.dist-info/RECORD
rcrepl-2.1.6.dist-info/WHEEL
rcrepl-2.1.6.dist-info/entry_points.txt
rcrepl-2.1.6.dist-info/metadata.json
rcrepl-2.1.6.dist-info/top_level.txt
