Metadata-Version: 2.0
Name: rcrepl
Version: 2.1.6
Summary: A python script that wraps a REPLs
Home-page: http://github.com/sras/rcrepl
Author: Sandeep.C.R
Author-email: sandeepcr2@gmail.com
License: MIT
Platform: UNKNOWN
Requires-Dist: pexpect
